{"stats":{"minecraft:picked_up":{"primordia:wooden_club":3},"minecraft:dropped":{"primordia:wooden_club":3},"minecraft:custom":{"minecraft:jump":99,"minecraft:time_since_rest":3402,"minecraft:crouch_one_cm":600,"minecraft:damage_taken":30,"minecraft:leave_game":2,"minecraft:play_time":3402,"minecraft:sprint_one_cm":5322,"minecraft:time_since_death":3402,"minecraft:walk_on_water_one_cm":34,"minecraft:walk_one_cm":7662,"minecraft:sneak_time":157,"minecraft:total_world_time":16903,"minecraft:drop":3,"minecraft:fall_one_cm":3250,"minecraft:fly_one_cm":27541},"minecraft:mined":{"minecraft:oak_leaves":11}},"DataVersion":3955}